mwptoolkit/__init__.py
mwptoolkit/hyper_search.py
mwptoolkit/quick_start.py
mwptoolkit/config/__init__.py
mwptoolkit/config/config.json
mwptoolkit/config/configuration.py
mwptoolkit/data/__init__.py
mwptoolkit/data/utils.py
mwptoolkit/data/dataloader/__init__.py
mwptoolkit/data/dataloader/abstract_dataloader.py
mwptoolkit/data/dataloader/dataloader_ept.py
mwptoolkit/data/dataloader/dataloader_gpt2.py
mwptoolkit/data/dataloader/dataloader_hms.py
mwptoolkit/data/dataloader/dataloader_multiencdec.py
mwptoolkit/data/dataloader/multi_equation_dataloader.py
mwptoolkit/data/dataloader/pretrain_dataloader.py
mwptoolkit/data/dataloader/single_equation_dataloader.py
mwptoolkit/data/dataloader/template_dataloader.py
mwptoolkit/data/dataset/__init__.py
mwptoolkit/data/dataset/abstract_dataset.py
mwptoolkit/data/dataset/dataset_ept.py
mwptoolkit/data/dataset/dataset_gpt2.py
mwptoolkit/data/dataset/dataset_hms.py
mwptoolkit/data/dataset/dataset_multiencdec.py
mwptoolkit/data/dataset/multi_equation_dataset.py
mwptoolkit/data/dataset/pretrain_dataset.py
mwptoolkit/data/dataset/single_equation_dataset.py
mwptoolkit/data/dataset/template_dataset.py
mwptoolkit/evaluate/__init__.py
mwptoolkit/evaluate/evaluator.py
mwptoolkit/loss/__init__.py
mwptoolkit/loss/abstract_loss.py
mwptoolkit/loss/binary_cross_entropy_loss.py
mwptoolkit/loss/cross_entropy_loss.py
mwptoolkit/loss/masked_cross_entropy_loss.py
mwptoolkit/loss/mse_loss.py
mwptoolkit/loss/nll_loss.py
mwptoolkit/loss/smoothed_cross_entropy_loss.py
mwptoolkit/model/__init__.py
mwptoolkit/model/abstract_model.py
mwptoolkit/model/GAN/__init__.py
mwptoolkit/model/GAN/seqgan.py
mwptoolkit/model/Graph2Tree/__init__.py
mwptoolkit/model/Graph2Tree/graph2tree.py
mwptoolkit/model/Graph2Tree/graph2treeibm.py
mwptoolkit/model/Graph2Tree/multiencdec.py
mwptoolkit/model/PreTrain/__init__.py
mwptoolkit/model/PreTrain/albertgen.py
mwptoolkit/model/PreTrain/bertgen.py
mwptoolkit-0.0.6.dist-info/METADATA
mwptoolkit-0.0.6.dist-info/RECORD
mwptoolkit-0.0.6.dist-info/WHEEL
mwptoolkit-0.0.6.dist-info/top_level.txt
