Metadata-Version: 2.1
Name: mwptoolkit
Version: 0.0.6
Summary: UNKNOWN
Home-page: https://github.com/LYH-YF/MWPToolkit
Author: 
License: UNKNOWN
Platform: UNKNOWN
Requires-Python: >=3.6.0
License-File: LICENSE
Requires-Dist: torch (>=1.5.0)
Requires-Dist: transformers (==4.3.3)
Requires-Dist: stanza (>=1.2)
Requires-Dist: sympy (>=1.6)
Requires-Dist: ray (>=1.3.0)
Requires-Dist: nltk (>=3.5)
Requires-Dist: gensim (>=4.0.1)
Requires-Dist: word2number (>=1.1)
Requires-Dist: ray[tune]
